{"paging": {"pageIndex": 1, "pageSize": 500, "total": 53}, "baseComponent": {"id": "AYH1GkysYGgAeaDMB6HJ", "key": "fga-eps-mds_2022-1-MeasureSoftGram-Core", "name": "2022-1-MeasureSoftGram-Core", "qualifier": "TRK", "measures": [{"metric": "duplicated_lines_density", "value": "0.0", "bestValue": true}, {"metric": "functions", "value": "35"}, {"metric": "test_execution_time", "value": "1672"}, {"metric": "test_failures", "value": "0", "bestValue": true}, {"metric": "test_errors", "value": "0", "bestValue": true}, {"metric": "security_rating", "value": "1.0", "bestValue": true}, {"metric": "tests", "value": "57"}, {"metric": "files", "value": "18"}, {"metric": "complexity", "value": "62"}, {"metric": "ncloc", "value": "641"}, {"metric": "coverage", "value": "85.1", "bestValue": false}, {"metric": "comment_lines_density", "value": "23.9", "bestValue": false}]}, "components": [{"id": "AYJaq_FEwtoZflRqqPI-", "key": "fga-eps-mds_2022-1-MeasureSoftGram-Core:tests/__init__.py", "name": "__init__.py", "qualifier": "UTS", "path": "tests/__init__.py", "language": "py", "measures": [{"metric": "security_rating", "value": "1.0", "bestValue": true}, {"metric": "test_errors", "value": "0", "bestValue": true}, {"metric": "duplicated_lines_density", "value": "0.0", "bestValue": true}, {"metric": "test_failures", "value": "0", "bestValue": true}]}, {"id": "AYJaq_FEwtoZflRqqPIz", "key": "fga-eps-mds_2022-1-MeasureSoftGram-Core:tests/utils/__init__.py", "name": "__init__.py", "qualifier": "UTS", "path": "tests/utils/__init__.py", "language": "py", "measures": [{"metric": "security_rating", "value": "1.0", "bestValue": true}, {"metric": "test_errors", "value": "0", "bestValue": true}, {"metric": "duplicated_lines_density", "value": "0.0", "bestValue": true}, {"metric": "test_failures", "value": "0", "bestValue": true}]}, {"id": "AYJaq_FEwtoZflRqqPI8", "key": "fga-eps-mds_2022-1-MeasureSoftGram-Core:tests/integration/__init__.py", "name": "__init__.py", "qualifier": "UTS", "path": "tests/integration/__init__.py", "language": "py", "measures": [{"metric": "security_rating", "value": "1.0", "bestValue": true}, {"metric": "test_errors", "value": "0", "bestValue": true}, {"metric": "duplicated_lines_density", "value": "0.0", "bestValue": true}, {"metric": "test_failures", "value": "0", "bestValue": true}]}, {"id": "AYJaq_FEwtoZflRqqPIx", "key": "fga-eps-mds_2022-1-MeasureSoftGram-Core:tests/unit/__init__.py", "name": "__init__.py", "qualifier": "UTS", "path": "tests/unit/__init__.py", "language": "py", "measures": [{"metric": "security_rating", "value": "1.0", "bestValue": true}, {"metric": "test_errors", "value": "0", "bestValue": true}, {"metric": "duplicated_lines_density", "value": "0.0", "bestValue": true}, {"metric": "test_failures", "value": "0", "bestValue": true}]}, {"id": "AYJaq_FEwtoZflRqqPIe", "key": "fga-eps-mds_2022-1-MeasureSoftGram-Core:src/__init__.py", "name": "__init__.py", "qualifier": "FIL", "path": "src/__init__.py", "language": "py", "measures": [{"metric": "complexity", "value": "0"}, {"metric": "functions", "value": "0"}, {"metric": "security_rating", "value": "1.0", "bestValue": true}, {"metric": "ncloc", "value": "0"}, {"metric": "files", "value": "1"}, {"metric": "test_errors", "value": "0", "bestValue": true}, {"metric": "duplicated_lines_density", "value": "0.0", "bestValue": true}, {"metric": "test_failures", "value": "0", "bestValue": true}]}, {"id": "AYJaq_FDwtoZflRqqPIM", "key": "fga-eps-mds_2022-1-MeasureSoftGram-Core:src/resources/__init__.py", "name": "__init__.py", "qualifier": "FIL", "path": "src/resources/__init__.py", "language": "py", "measures": [{"metric": "complexity", "value": "0"}, {"metric": "functions", "value": "0"}, {"metric": "security_rating", "value": "1.0", "bestValue": true}, {"metric": "ncloc", "value": "0"}, {"metric": "files", "value": "1"}, {"metric": "test_errors", "value": "0", "bestValue": true}, {"metric": "duplicated_lines_density", "value": "0.0", "bestValue": true}, {"metric": "test_failures", "value": "0", "bestValue": true}]}, {"id": "AYJaq_FDwtoZflRqqPIS", "key": "fga-eps-mds_2022-1-MeasureSoftGram-Core:src/core/__init__.py", "name": "__init__.py", "qualifier": "FIL", "path": "src/core/__init__.py", "language": "py", "measures": [{"metric": "complexity", "value": "0"}, {"metric": "functions", "value": "0"}, {"metric": "security_rating", "value": "1.0", "bestValue": true}, {"metric": "ncloc", "value": "0"}, {"metric": "files", "value": "1"}, {"metric": "test_errors", "value": "0", "bestValue": true}, {"metric": "duplicated_lines_density", "value": "0.0", "bestValue": true}, {"metric": "test_failures", "value": "0", "bestValue": true}]}, {"id": "AYJaq_FEwtoZflRqqPIc", "key": "fga-eps-mds_2022-1-MeasureSoftGram-Core:src/util/__init__.py", "name": "__init__.py", "qualifier": "FIL", "path": "src/util/__init__.py", "language": "py", "measures": [{"metric": "complexity", "value": "0"}, {"metric": "functions", "value": "0"}, {"metric": "security_rating", "value": "1.0", "bestValue": true}, {"metric": "ncloc", "value": "0"}, {"metric": "files", "value": "1"}, {"metric": "test_errors", "value": "0", "bestValue": true}, {"metric": "duplicated_lines_density", "value": "0.0", "bestValue": true}, {"metric": "test_failures", "value": "0", "bestValue": true}]}, {"id": "AYJaq_FEwtoZflRqqPI4", "key": "fga-eps-mds_2022-1-MeasureSoftGram-Core:tests/utils/aggregation_data.py", "name": "aggregation_data.py", "qualifier": "UTS", "path": "tests/utils/aggregation_data.py", "language": "py", "measures": [{"metric": "security_rating", "value": "1.0", "bestValue": true}, {"metric": "test_errors", "value": "0", "bestValue": true}, {"metric": "duplicated_lines_density", "value": "0.0", "bestValue": true}, {"metric": "test_failures", "value": "0", "bestValue": true}]}, {"id": "AYJaq_FDwtoZflRqqPIV", "key": "fga-eps-mds_2022-1-MeasureSoftGram-Core:src/core/agregation.py", "name": "agregation.py", "qualifier": "FIL", "path": "src/core/agregation.py", "language": "py", "measures": [{"metric": "complexity", "value": "1"}, {"metric": "functions", "value": "1"}, {"metric": "ncloc", "value": "7"}, {"metric": "coverage", "value": "100.0", "bestValue": true}, {"metric": "security_rating", "value": "1.0", "bestValue": true}, {"metric": "comment_lines_density", "value": "0.0", "bestValue": false}, {"metric": "files", "value": "1"}, {"metric": "test_errors", "value": "0", "bestValue": true}, {"metric": "duplicated_lines_density", "value": "0.0", "bestValue": true}, {"metric": "test_failures", "value": "0", "bestValue": true}]}, {"id": "AYJaq_FDwtoZflRqqPIN", "key": "fga-eps-mds_2022-1-MeasureSoftGram-Core:src/resources/analysis.py", "name": "analysis.py", "qualifier": "FIL", "path": "src/resources/analysis.py", "language": "py", "measures": [{"metric": "complexity", "value": "4"}, {"metric": "functions", "value": "2"}, {"metric": "ncloc", "value": "81"}, {"metric": "coverage", "value": "50.0", "bestValue": false}, {"metric": "security_rating", "value": "1.0", "bestValue": true}, {"metric": "comment_lines_density", "value": "2.4", "bestValue": false}, {"metric": "files", "value": "1"}, {"metric": "test_errors", "value": "0", "bestValue": true}, {"metric": "duplicated_lines_density", "value": "0.0", "bestValue": true}, {"metric": "test_failures", "value": "0", "bestValue": true}]}, {"id": "AYJaq_FDwtoZflRqqPIT", "key": "fga-eps-mds_2022-1-MeasureSoftGram-Core:src/core/analysis.py", "name": "analysis.py", "qualifier": "FIL", "path": "src/core/analysis.py", "language": "py", "measures": [{"metric": "complexity", "value": "8"}, {"metric": "functions", "value": "3"}, {"metric": "ncloc", "value": "59"}, {"metric": "coverage", "value": "100.0", "bestValue": true}, {"metric": "security_rating", "value": "1.0", "bestValue": true}, {"metric": "comment_lines_density", "value": "0.0", "bestValue": false}, {"metric": "files", "value": "1"}, {"metric": "test_errors", "value": "0", "bestValue": true}, {"metric": "duplicated_lines_density", "value": "0.0", "bestValue": true}, {"metric": "test_failures", "value": "0", "bestValue": true}]}, {"id": "AYJaq_FEwtoZflRqqPI0", "key": "fga-eps-mds_2022-1-MeasureSoftGram-Core:tests/utils/analysis_data.py", "name": "analysis_data.py", "qualifier": "UTS", "path": "tests/utils/analysis_data.py", "language": "py", "measures": [{"metric": "security_rating", "value": "1.0", "bestValue": true}, {"metric": "test_errors", "value": "0", "bestValue": true}, {"metric": "duplicated_lines_density", "value": "0.0", "bestValue": true}, {"metric": "test_failures", "value": "0", "bestValue": true}]}, {"id": "AYJaq_FEwtoZflRqqPIf", "key": "fga-eps-mds_2022-1-MeasureSoftGram-Core:src/app.py", "name": "app.py", "qualifier": "FIL", "path": "src/app.py", "language": "py", "measures": [{"metric": "complexity", "value": "0"}, {"metric": "functions", "value": "0"}, {"metric": "ncloc", "value": "11"}, {"metric": "coverage", "value": "100.0", "bestValue": true}, {"metric": "security_rating", "value": "1.0", "bestValue": true}, {"metric": "comment_lines_density", "value": "0.0", "bestValue": false}, {"metric": "files", "value": "1"}, {"metric": "test_errors", "value": "0", "bestValue": true}, {"metric": "duplicated_lines_density", "value": "0.0", "bestValue": true}, {"metric": "test_failures", "value": "0", "bestValue": true}]}, {"id": "AYJaq_FDwtoZflRqqPIL", "key": "fga-eps-mds_2022-1-MeasureSoftGram-Core:src/resources/available.py", "name": "available.py", "qualifier": "FIL", "path": "src/resources/available.py", "language": "py", "measures": [{"metric": "complexity", "value": "1"}, {"metric": "functions", "value": "1"}, {"metric": "ncloc", "value": "6"}, {"metric": "coverage", "value": "83.3", "bestValue": false}, {"metric": "security_rating", "value": "1.0", "bestValue": true}, {"metric": "comment_lines_density", "value": "0.0", "bestValue": false}, {"metric": "files", "value": "1"}, {"metric": "test_errors", "value": "0", "bestValue": true}, {"metric": "duplicated_lines_density", "value": "0.0", "bestValue": true}, {"metric": "test_failures", "value": "0", "bestValue": true}]}, {"id": "AYJaq_FEwtoZflRqqPIm", "key": "fga-eps-mds_2022-1-MeasureSoftGram-Core:tests/unit/data/between_zero_and_one_coverage.json", "name": "between_zero_and_one_coverage.json", "qualifier": "UTS", "path": "tests/unit/data/between_zero_and_one_coverage.json", "language": "json", "measures": [{"metric": "security_rating", "value": "1.0", "bestValue": true}, {"metric": "test_errors", "value": "0", "bestValue": true}, {"metric": "duplicated_lines_density", "value": "0.0", "bestValue": true}, {"metric": "test_failures", "value": "0", "bestValue": true}]}, {"id": "AYJaq_FEwtoZflRqqPIY", "key": "fga-eps-mds_2022-1-MeasureSoftGram-Core:src/util/check_functions.py", "name": "check_functions.py", "qualifier": "FIL", "path": "src/util/check_functions.py", "language": "py", "measures": [{"metric": "complexity", "value": "11"}, {"metric": "functions", "value": "5"}, {"metric": "ncloc", "value": "26"}, {"metric": "coverage", "value": "95.0", "bestValue": false}, {"metric": "security_rating", "value": "1.0", "bestValue": true}, {"metric": "comment_lines_density", "value": "18.8", "bestValue": false}, {"metric": "files", "value": "1"}, {"metric": "test_errors", "value": "0", "bestValue": true}, {"metric": "duplicated_lines_density", "value": "0.0", "bestValue": true}, {"metric": "test_failures", "value": "0", "bestValue": true}]}, {"id": "AYJaq_FEwtoZflRqqPIZ", "key": "fga-eps-mds_2022-1-MeasureSoftGram-Core:src/util/constants.py", "name": "constants.py", "qualifier": "FIL", "path": "src/util/constants.py", "language": "py", "measures": [{"metric": "complexity", "value": "0"}, {"metric": "functions", "value": "0"}, {"metric": "ncloc", "value": "138"}, {"metric": "coverage", "value": "100.0", "bestValue": true}, {"metric": "security_rating", "value": "1.0", "bestValue": true}, {"metric": "comment_lines_density", "value": "0.0", "bestValue": false}, {"metric": "files", "value": "1"}, {"metric": "test_errors", "value": "0", "bestValue": true}, {"metric": "duplicated_lines_density", "value": "0.0", "bestValue": true}, {"metric": "test_failures", "value": "0", "bestValue": true}]}, {"id": "AYJaq_FEwtoZflRqqPIX", "key": "fga-eps-mds_2022-1-MeasureSoftGram-Core:src/core", "name": "core", "qualifier": "DIR", "path": "src/core", "measures": [{"metric": "duplicated_lines_density", "value": "0.0", "bestValue": true}, {"metric": "functions", "value": "24"}, {"metric": "security_rating", "value": "1.0", "bestValue": true}, {"metric": "files", "value": "8"}, {"metric": "complexity", "value": "42"}, {"metric": "ncloc", "value": "359"}, {"metric": "coverage", "value": "88.5", "bestValue": false}, {"metric": "comment_lines_density", "value": "33.4", "bestValue": false}]}, {"id": "AYJaq_FEwtoZflRqqPIs", "key": "fga-eps-mds_2022-1-MeasureSoftGram-Core:tests/unit/data", "name": "data", "qualifier": "DIR", "path": "tests/unit/data", "measures": [{"metric": "security_rating", "value": "1.0", "bestValue": true}]}, {"id": "AYJaq_FDwtoZflRqqPIR", "key": "fga-eps-mds_2022-1-MeasureSoftGram-Core:src/core/dataframe.py", "name": "dataframe.py", "qualifier": "FIL", "path": "src/core/dataframe.py", "language": "py", "measures": [{"metric": "complexity", "value": "4"}, {"metric": "functions", "value": "1"}, {"metric": "ncloc", "value": "12"}, {"metric": "coverage", "value": "100.0", "bestValue": true}, {"metric": "security_rating", "value": "1.0", "bestValue": true}, {"metric": "comment_lines_density", "value": "0.0", "bestValue": false}, {"metric": "files", "value": "1"}, {"metric": "test_errors", "value": "0", "bestValue": true}, {"metric": "duplicated_lines_density", "value": "0.0", "bestValue": true}, {"metric": "test_failures", "value": "0", "bestValue": true}]}, {"id": "AYJaq_FEwtoZflRqqPIb", "key": "fga-eps-mds_2022-1-MeasureSoftGram-Core:src/util/exceptions.py", "name": "exceptions.py", "qualifier": "FIL", "path": "src/util/exceptions.py", "language": "py", "measures": [{"metric": "complexity", "value": "0"}, {"metric": "functions", "value": "0"}, {"metric": "ncloc", "value": "8"}, {"metric": "coverage", "value": "100.0", "bestValue": true}, {"metric": "security_rating", "value": "1.0", "bestValue": true}, {"metric": "comment_lines_density", "value": "33.3", "bestValue": false}, {"metric": "files", "value": "1"}, {"metric": "test_errors", "value": "0", "bestValue": true}, {"metric": "duplicated_lines_density", "value": "0.0", "bestValue": true}, {"metric": "test_failures", "value": "0", "bestValue": true}]}, {"id": "AYJaq_FEwtoZflRqqPIr", "key": "fga-eps-mds_2022-1-MeasureSoftGram-Core:tests/unit/data/fga-eps-mds-2020_2-Lend.it-Raleway-user-13-04-2021.json", "name": "fga-eps-mds-2020_2-Lend.it-Raleway-user-13-04-2021.json", "qualifier": "UTS", "path": "tests/unit/data/fga-eps-mds-2020_2-Lend.it-Raleway-user-13-04-2021.json", "language": "json", "measures": [{"metric": "security_rating", "value": "1.0", "bestValue": true}, {"metric": "test_errors", "value": "0", "bestValue": true}, {"metric": "duplicated_lines_density", "value": "0.0", "bestValue": true}, {"metric": "test_failures", "value": "0", "bestValue": true}]}, {"id": "AYJaq_FEwtoZflRqqPIo", "key": "fga-eps-mds_2022-1-MeasureSoftGram-Core:tests/unit/data/fga-eps-mds-2020_2-Projeto-Kokama-Usuario-17-04-2021.json", "name": "fga-eps-mds-2020_2-Projeto-Kokama-Usuario-17-04-2021.json", "qualifier": "UTS", "path": "tests/unit/data/fga-eps-mds-2020_2-Projeto-Kokama-Usuario-17-04-2021.json", "language": "json", "measures": [{"metric": "security_rating", "value": "1.0", "bestValue": true}, {"metric": "test_errors", "value": "0", "bestValue": true}, {"metric": "duplicated_lines_density", "value": "0.0", "bestValue": true}, {"metric": "test_failures", "value": "0", "bestValue": true}]}, {"id": "AYJaq_FEwtoZflRqqPIi", "key": "fga-eps-mds_2022-1-MeasureSoftGram-Core:tests/unit/data/fga-eps-mds-2021-2-MeasureSoftGram-CLI-04-13-2022-02-13-37-v1.1.1.json", "name": "fga-eps-mds-2021-2-MeasureSoftGram-CLI-04-13-2022-02-13-37-v1.1.1.json", "qualifier": "UTS", "path": "tests/unit/data/fga-eps-mds-2021-2-MeasureSoftGram-CLI-04-13-2022-02-13-37-v1.1.1.json", "language": "json", "measures": [{"metric": "security_rating", "value": "1.0", "bestValue": true}, {"metric": "test_errors", "value": "0", "bestValue": true}, {"metric": "duplicated_lines_density", "value": "0.0", "bestValue": true}, {"metric": "test_failures", "value": "0", "bestValue": true}]}, {"id": "AYJaq_FEwtoZflRqqPIk", "key": "fga-eps-mds_2022-1-MeasureSoftGram-Core:tests/unit/data/fga-eps-mds-2021-2-MeasureSoftGram-Service-04-12-2022-17-32-35-v1.1.0.json", "name": "fga-eps-mds-2021-2-MeasureSoftGram-Service-04-12-2022-17-32-35-v1.1.0.json", "qualifier": "UTS", "path": "tests/unit/data/fga-eps-mds-2021-2-MeasureSoftGram-Service-04-12-2022-17-32-35-v1.1.0.json", "language": "json", "measures": [{"metric": "security_rating", "value": "1.0", "bestValue": true}, {"metric": "test_errors", "value": "0", "bestValue": true}, {"metric": "duplicated_lines_density", "value": "0.0", "bestValue": true}, {"metric": "test_failures", "value": "0", "bestValue": true}]}, {"id": "AYJaq_FEwtoZflRqqPIq", "key": "fga-eps-mds_2022-1-MeasureSoftGram-Core:tests/unit/data/fga-eps-mds_2021-2-SiGeD-Frontend-03-15-2022-23_57_08.json", "name": "fga-eps-mds_2021-2-SiGeD-Frontend-03-15-2022-23_57_08.json", "qualifier": "UTS", "path": "tests/unit/data/fga-eps-mds_2021-2-SiGeD-Frontend-03-15-2022-23_57_08.json", "language": "json", "measures": [{"metric": "security_rating", "value": "1.0", "bestValue": true}, {"metric": "test_errors", "value": "0", "bestValue": true}, {"metric": "duplicated_lines_density", "value": "0.0", "bestValue": true}, {"metric": "test_failures", "value": "0", "bestValue": true}]}, {"id": "AYJaq_FEwtoZflRqqPIa", "key": "fga-eps-mds_2022-1-MeasureSoftGram-Core:src/util/get_functions.py", "name": "get_functions.py", "qualifier": "FIL", "path": "src/util/get_functions.py", "language": "py", "measures": [{"metric": "complexity", "value": "4"}, {"metric": "functions", "value": "3"}, {"metric": "ncloc", "value": "12"}, {"metric": "coverage", "value": "100.0", "bestValue": true}, {"metric": "security_rating", "value": "1.0", "bestValue": true}, {"metric": "comment_lines_density", "value": "42.9", "bestValue": false}, {"metric": "files", "value": "1"}, {"metric": "test_errors", "value": "0", "bestValue": true}, {"metric": "duplicated_lines_density", "value": "0.0", "bestValue": true}, {"metric": "test_failures", "value": "0", "bestValue": true}]}, {"id": "AYJaq_FEwtoZflRqqPI9", "key": "fga-eps-mds_2022-1-MeasureSoftGram-Core:tests/integration", "name": "integration", "qualifier": "DIR", "path": "tests/integration", "measures": [{"metric": "test_execution_time", "value": "165"}, {"metric": "test_failures", "value": "0", "bestValue": true}, {"metric": "test_errors", "value": "0", "bestValue": true}, {"metric": "security_rating", "value": "1.0", "bestValue": true}, {"metric": "tests", "value": "3"}]}, {"id": "AYJaq_FEwtoZflRqqPI2", "key": "fga-eps-mds_2022-1-MeasureSoftGram-Core:tests/utils/integration_data.py", "name": "integration_data.py", "qualifier": "UTS", "path": "tests/utils/integration_data.py", "language": "py", "measures": [{"metric": "security_rating", "value": "1.0", "bestValue": true}, {"metric": "test_errors", "value": "0", "bestValue": true}, {"metric": "duplicated_lines_density", "value": "0.0", "bestValue": true}, {"metric": "test_failures", "value": "0", "bestValue": true}]}, {"id": "AYJaq_FDwtoZflRqqPIP", "key": "fga-eps-mds_2022-1-MeasureSoftGram-Core:src/core/interpretation_functions.py", "name": "interpretation_functions.py", "qualifier": "FIL", "path": "src/core/interpretation_functions.py", "language": "py", "measures": [{"metric": "complexity", "value": "10"}, {"metric": "functions", "value": "8"}, {"metric": "ncloc", "value": "122"}, {"metric": "coverage", "value": "78.3", "bestValue": false}, {"metric": "security_rating", "value": "1.0", "bestValue": true}, {"metric": "comment_lines_density", "value": "34.1", "bestValue": false}, {"metric": "files", "value": "1"}, {"metric": "test_errors", "value": "0", "bestValue": true}, {"metric": "duplicated_lines_density", "value": "0.0", "bestValue": true}, {"metric": "test_failures", "value": "0", "bestValue": true}]}, {"id": "AYJaq_FEwtoZflRqqPI1", "key": "fga-eps-mds_2022-1-MeasureSoftGram-Core:tests/utils/interpretation_functions_data.py", "name": "interpretation_functions_data.py", "qualifier": "UTS", "path": "tests/utils/interpretation_functions_data.py", "language": "py", "measures": [{"metric": "security_rating", "value": "1.0", "bestValue": true}, {"metric": "test_errors", "value": "0", "bestValue": true}, {"metric": "duplicated_lines_density", "value": "0.0", "bestValue": true}, {"metric": "test_failures", "value": "0", "bestValue": true}]}, {"id": "AYJaq_FEwtoZflRqqPIj", "key": "fga-eps-mds_2022-1-MeasureSoftGram-Core:tests/unit/data/invalid_commented_lines_density.json", "name": "invalid_commented_lines_density.json", "qualifier": "UTS", "path": "tests/unit/data/invalid_commented_lines_density.json", "language": "json", "measures": [{"metric": "security_rating", "value": "1.0", "bestValue": true}, {"metric": "test_errors", "value": "0", "bestValue": true}, {"metric": "duplicated_lines_density", "value": "0.0", "bestValue": true}, {"metric": "test_failures", "value": "0", "bestValue": true}]}, {"id": "AYJaq_FEwtoZflRqqPIp", "key": "fga-eps-mds_2022-1-MeasureSoftGram-Core:tests/unit/data/invalid_complexity_value.json", "name": "invalid_complexity_value.json", "qualifier": "UTS", "path": "tests/unit/data/invalid_complexity_value.json", "language": "json", "measures": [{"metric": "security_rating", "value": "1.0", "bestValue": true}, {"metric": "test_errors", "value": "0", "bestValue": true}, {"metric": "duplicated_lines_density", "value": "0.0", "bestValue": true}, {"metric": "test_failures", "value": "0", "bestValue": true}]}, {"id": "AYJaq_FDwtoZflRqqPIU", "key": "fga-eps-mds_2022-1-MeasureSoftGram-Core:src/core/measures_functions.py", "name": "measures_functions.py", "qualifier": "FIL", "path": "src/core/measures_functions.py", "language": "py", "measures": [{"metric": "complexity", "value": "17"}, {"metric": "functions", "value": "10"}, {"metric": "ncloc", "value": "120"}, {"metric": "coverage", "value": "83.9", "bestValue": false}, {"metric": "security_rating", "value": "1.0", "bestValue": true}, {"metric": "comment_lines_density", "value": "33.7", "bestValue": false}, {"metric": "files", "value": "1"}, {"metric": "test_errors", "value": "0", "bestValue": true}, {"metric": "duplicated_lines_density", "value": "0.0", "bestValue": true}, {"metric": "test_failures", "value": "0", "bestValue": true}]}, {"id": "AYJaq_FDwtoZflRqqPIO", "key": "fga-eps-mds_2022-1-MeasureSoftGram-Core:src/resources", "name": "resources", "qualifier": "DIR", "path": "src/resources", "measures": [{"metric": "duplicated_lines_density", "value": "0.0", "bestValue": true}, {"metric": "functions", "value": "3"}, {"metric": "security_rating", "value": "1.0", "bestValue": true}, {"metric": "files", "value": "3"}, {"metric": "complexity", "value": "5"}, {"metric": "ncloc", "value": "87"}, {"metric": "coverage", "value": "54.0", "bestValue": false}, {"metric": "comment_lines_density", "value": "2.2", "bestValue": false}]}, {"id": "AYJaq_FDwtoZflRqqPIW", "key": "fga-eps-mds_2022-1-MeasureSoftGram-Core:src/core/schemas.py", "name": "schemas.py", "qualifier": "FIL", "path": "src/core/schemas.py", "language": "py", "measures": [{"metric": "complexity", "value": "0"}, {"metric": "functions", "value": "0"}, {"metric": "ncloc", "value": "31"}, {"metric": "coverage", "value": "100.0", "bestValue": true}, {"metric": "security_rating", "value": "1.0", "bestValue": true}, {"metric": "comment_lines_density", "value": "64.4", "bestValue": false}, {"metric": "files", "value": "1"}, {"metric": "test_errors", "value": "0", "bestValue": true}, {"metric": "duplicated_lines_density", "value": "0.0", "bestValue": true}, {"metric": "test_failures", "value": "0", "bestValue": true}]}, {"id": "AYJaq_FEwtoZflRqqPIg", "key": "fga-eps-mds_2022-1-MeasureSoftGram-Core:src", "name": "src", "qualifier": "DIR", "path": "src", "measures": [{"metric": "duplicated_lines_density", "value": "0.0", "bestValue": true}, {"metric": "functions", "value": "35"}, {"metric": "security_rating", "value": "1.0", "bestValue": true}, {"metric": "files", "value": "18"}, {"metric": "complexity", "value": "62"}, {"metric": "ncloc", "value": "641"}, {"metric": "coverage", "value": "85.1", "bestValue": false}, {"metric": "comment_lines_density", "value": "23.9", "bestValue": false}]}, {"id": "AYJaq_FEwtoZflRqqPIu", "key": "fga-eps-mds_2022-1-MeasureSoftGram-Core:tests/unit/test_agregation.py", "name": "test_agregation.py", "qualifier": "UTS", "path": "tests/unit/test_agregation.py", "language": "py", "measures": [{"metric": "security_rating", "value": "1.0", "bestValue": true}, {"metric": "test_execution_time", "value": "2"}, {"metric": "tests", "value": "1"}, {"metric": "test_errors", "value": "0", "bestValue": true}, {"metric": "duplicated_lines_density", "value": "0.0", "bestValue": true}, {"metric": "test_failures", "value": "0", "bestValue": true}]}, {"id": "AYJaq_FEwtoZflRqqPI7", "key": "fga-eps-mds_2022-1-MeasureSoftGram-Core:tests/integration/test_analysis.py", "name": "test_analysis.py", "qualifier": "UTS", "path": "tests/integration/test_analysis.py", "language": "py", "measures": [{"metric": "security_rating", "value": "1.0", "bestValue": true}, {"metric": "test_execution_time", "value": "165"}, {"metric": "tests", "value": "3"}, {"metric": "test_errors", "value": "0", "bestValue": true}, {"metric": "duplicated_lines_density", "value": "0.0", "bestValue": true}, {"metric": "test_failures", "value": "0", "bestValue": true}]}, {"id": "AYJaq_FEwtoZflRqqPIw", "key": "fga-eps-mds_2022-1-MeasureSoftGram-Core:tests/unit/test_analysis.py", "name": "test_analysis.py", "qualifier": "UTS", "path": "tests/unit/test_analysis.py", "language": "py", "measures": [{"metric": "security_rating", "value": "1.0", "bestValue": true}, {"metric": "test_execution_time", "value": "12"}, {"metric": "tests", "value": "5"}, {"metric": "test_errors", "value": "0", "bestValue": true}, {"metric": "duplicated_lines_density", "value": "0.0", "bestValue": true}, {"metric": "test_failures", "value": "0", "bestValue": true}]}, {"id": "AYJaq_FEwtoZflRqqPI6", "key": "fga-eps-mds_2022-1-MeasureSoftGram-Core:tests/test_helpers.py", "name": "test_helpers.py", "qualifier": "UTS", "path": "tests/test_helpers.py", "language": "py", "measures": [{"metric": "security_rating", "value": "1.0", "bestValue": true}, {"metric": "test_errors", "value": "0", "bestValue": true}, {"metric": "duplicated_lines_density", "value": "0.0", "bestValue": true}, {"metric": "test_failures", "value": "0", "bestValue": true}]}, {"id": "AYJaq_FEwtoZflRqqPIt", "key": "fga-eps-mds_2022-1-MeasureSoftGram-Core:tests/unit/test_interpretation_functions.py", "name": "test_interpretation_functions.py", "qualifier": "UTS", "path": "tests/unit/test_interpretation_functions.py", "language": "py", "measures": [{"metric": "security_rating", "value": "1.0", "bestValue": true}, {"metric": "test_execution_time", "value": "1482"}, {"metric": "tests", "value": "39"}, {"metric": "test_errors", "value": "0", "bestValue": true}, {"metric": "duplicated_lines_density", "value": "0.0", "bestValue": true}, {"metric": "test_failures", "value": "0", "bestValue": true}]}, {"id": "AYJaq_FEwtoZflRqqPIv", "key": "fga-eps-mds_2022-1-MeasureSoftGram-Core:tests/unit/test_weighting.py", "name": "test_weighting.py", "qualifier": "UTS", "path": "tests/unit/test_weighting.py", "language": "py", "measures": [{"metric": "security_rating", "value": "1.0", "bestValue": true}, {"metric": "test_execution_time", "value": "11"}, {"metric": "tests", "value": "9"}, {"metric": "test_errors", "value": "0", "bestValue": true}, {"metric": "duplicated_lines_density", "value": "0.0", "bestValue": true}, {"metric": "test_failures", "value": "0", "bestValue": true}]}, {"id": "AYJaq_FEwtoZflRqqPI_", "key": "fga-eps-mds_2022-1-MeasureSoftGram-Core:tests", "name": "tests", "qualifier": "DIR", "path": "tests", "measures": [{"metric": "test_execution_time", "value": "1672"}, {"metric": "test_failures", "value": "0", "bestValue": true}, {"metric": "test_errors", "value": "0", "bestValue": true}, {"metric": "security_rating", "value": "1.0", "bestValue": true}, {"metric": "tests", "value": "57"}]}, {"id": "AYJaq_FEwtoZflRqqPIy", "key": "fga-eps-mds_2022-1-MeasureSoftGram-Core:tests/unit", "name": "unit", "qualifier": "DIR", "path": "tests/unit", "measures": [{"metric": "test_execution_time", "value": "1507"}, {"metric": "test_failures", "value": "0", "bestValue": true}, {"metric": "test_errors", "value": "0", "bestValue": true}, {"metric": "security_rating", "value": "1.0", "bestValue": true}, {"metric": "tests", "value": "54"}]}, {"id": "AYJaq_FEwtoZflRqqPId", "key": "fga-eps-mds_2022-1-MeasureSoftGram-Core:src/util", "name": "util", "qualifier": "DIR", "path": "src/util", "measures": [{"metric": "duplicated_lines_density", "value": "0.0", "bestValue": true}, {"metric": "functions", "value": "8"}, {"metric": "security_rating", "value": "1.0", "bestValue": true}, {"metric": "files", "value": "5"}, {"metric": "complexity", "value": "15"}, {"metric": "ncloc", "value": "184"}, {"metric": "coverage", "value": "97.7", "bestValue": false}, {"metric": "comment_lines_density", "value": "9.4", "bestValue": false}]}, {"id": "AYJaq_FEwtoZflRqqPI5", "key": "fga-eps-mds_2022-1-MeasureSoftGram-Core:tests/utils", "name": "utils", "qualifier": "DIR", "path": "tests/utils", "measures": [{"metric": "security_rating", "value": "1.0", "bestValue": true}]}, {"id": "AYJaq_FDwtoZflRqqPIQ", "key": "fga-eps-mds_2022-1-MeasureSoftGram-Core:src/core/weighting.py", "name": "weighting.py", "qualifier": "FIL", "path": "src/core/weighting.py", "language": "py", "measures": [{"metric": "complexity", "value": "2"}, {"metric": "functions", "value": "1"}, {"metric": "ncloc", "value": "8"}, {"metric": "coverage", "value": "100.0", "bestValue": true}, {"metric": "security_rating", "value": "1.0", "bestValue": true}, {"metric": "comment_lines_density", "value": "0.0", "bestValue": false}, {"metric": "files", "value": "1"}, {"metric": "test_errors", "value": "0", "bestValue": true}, {"metric": "duplicated_lines_density", "value": "0.0", "bestValue": true}, {"metric": "test_failures", "value": "0", "bestValue": true}]}, {"id": "AYJaq_FEwtoZflRqqPI3", "key": "fga-eps-mds_2022-1-MeasureSoftGram-Core:tests/utils/weighting_data.py", "name": "weighting_data.py", "qualifier": "UTS", "path": "tests/utils/weighting_data.py", "language": "py", "measures": [{"metric": "security_rating", "value": "1.0", "bestValue": true}, {"metric": "test_errors", "value": "0", "bestValue": true}, {"metric": "duplicated_lines_density", "value": "0.0", "bestValue": true}, {"metric": "test_failures", "value": "0", "bestValue": true}]}, {"id": "AYJaq_FEwtoZflRqqPIn", "key": "fga-eps-mds_2022-1-MeasureSoftGram-Core:tests/unit/data/zero_cyclomatic_complexity.json", "name": "zero_cyclomatic_complexity.json", "qualifier": "UTS", "path": "tests/unit/data/zero_cyclomatic_complexity.json", "language": "json", "measures": [{"metric": "security_rating", "value": "1.0", "bestValue": true}, {"metric": "test_errors", "value": "0", "bestValue": true}, {"metric": "duplicated_lines_density", "value": "0.0", "bestValue": true}, {"metric": "test_failures", "value": "0", "bestValue": true}]}, {"id": "AYJaq_FEwtoZflRqqPIh", "key": "fga-eps-mds_2022-1-MeasureSoftGram-Core:tests/unit/data/zero_number_of_files.json", "name": "zero_number_of_files.json", "qualifier": "UTS", "path": "tests/unit/data/zero_number_of_files.json", "language": "json", "measures": [{"metric": "security_rating", "value": "1.0", "bestValue": true}, {"metric": "test_errors", "value": "0", "bestValue": true}, {"metric": "duplicated_lines_density", "value": "0.0", "bestValue": true}, {"metric": "test_failures", "value": "0", "bestValue": true}]}, {"id": "AYJaq_FEwtoZflRqqPIl", "key": "fga-eps-mds_2022-1-MeasureSoftGram-Core:tests/unit/data/zero_number_of_functions.json", "name": "zero_number_of_functions.json", "qualifier": "UTS", "path": "tests/unit/data/zero_number_of_functions.json", "language": "json", "measures": [{"metric": "security_rating", "value": "1.0", "bestValue": true}, {"metric": "test_errors", "value": "0", "bestValue": true}, {"metric": "duplicated_lines_density", "value": "0.0", "bestValue": true}, {"metric": "test_failures", "value": "0", "bestValue": true}]}]}